frostypy/__init__.py
frostypy/core.py
frostypy/density.py
frostypy/porosity.py
frostypy/thermal_conductivity.py
frostypy/thickness.py
frostypy-0.0.17.data/data/my_data/data_file
frostypy-0.0.17.dist-info/LICENSE.txt
frostypy-0.0.17.dist-info/METADATA
frostypy-0.0.17.dist-info/WHEEL
frostypy-0.0.17.dist-info/entry_points.txt
frostypy-0.0.17.dist-info/top_level.txt
frostypy-0.0.17.dist-info/RECORD
